how-tos/__init__.py
how-tos/consts.py
how-tos/utils.py
how-tos/confidential_storage/__init__.py
how-tos/confidential_storage/main.py
how-tos/customize_trust_environment/__init__.py
how-tos/robotic_process_automation/__init__.py
how-tos/robotic_process_automation/main.py
sirius_sdk/__init__.py
sirius_sdk/base.py
sirius_sdk/abstract/__init__.py
sirius_sdk/abstract/api.py
sirius_sdk/abstract/batching.py
sirius_sdk/abstract/bus.py
sirius_sdk/abstract/listener.py
sirius_sdk/abstract/p2p.py
sirius_sdk/abstract/storage.py
sirius_sdk/agent/__init__.py
sirius_sdk/agent/agent.py
sirius_sdk/agent/bus.py
sirius_sdk/agent/codec.py
sirius_sdk/agent/connections.py
sirius_sdk/agent/dkms.py
sirius_sdk/agent/listener.py
sirius_sdk/agent/pairwise.py
sirius_sdk/agent/storages.py
sirius_sdk/agent/aries_rfc/__init__.py
sirius_sdk/agent/aries_rfc/base.py
sirius_sdk/agent/aries_rfc/decorators.py
sirius_sdk/agent/aries_rfc/did_doc.py
sirius_sdk/agent/aries_rfc/mixins.py
sirius_sdk/agent/aries_rfc/utils.py
sirius_sdk/agent/aries_rfc/feature_0015_acks/__init__.py
sirius_sdk/agent/aries_rfc/feature_0015_acks/messages.py
sirius_sdk/agent/aries_rfc/feature_0036_issue_credential/__init__.py
sirius_sdk/agent/aries_rfc/feature_0036_issue_credential/messages.py
sirius_sdk/agent/aries_rfc/feature_0036_issue_credential/state_machines.py
sirius_sdk/agent/aries_rfc/feature_0037_present_proof/__init__.py
sirius_sdk/agent/aries_rfc/feature_0037_present_proof/error_codes.py
sirius_sdk/agent/aries_rfc/feature_0037_present_proof/interactive.py
sirius_sdk/agent/aries_rfc/feature_0037_present_proof/messages.py
sirius_sdk/agent/aries_rfc/feature_0037_present_proof/state_machines.py
sirius_sdk/agent/aries_rfc/feature_0048_trust_ping/__init__.py
sirius_sdk/agent/aries_rfc/feature_0048_trust_ping/messages.py
sirius_sdk/agent/aries_rfc/feature_0095_basic_message/__init__.py
sirius_sdk/agent/aries_rfc/feature_0095_basic_message/messages.py
sirius_sdk/agent/aries_rfc/feature_0113_question_answer/__init__.py
sirius_sdk-2.2.0.dist-info/LICENSE
sirius_sdk-2.2.0.dist-info/METADATA
sirius_sdk-2.2.0.dist-info/WHEEL
sirius_sdk-2.2.0.dist-info/top_level.txt
sirius_sdk-2.2.0.dist-info/RECORD
