Metadata-Version: 2.1
Name: sirius-sdk
Version: 2.2.0
Summary: SDK for developing Smart-Contracts in Self-sovereign-identity world.
Home-page: https://github.com/Sirius-social/sirius-sdk-python
Author: Networks Synergy
Author-email: support@socialsirius.com
Maintainer: Pavel Minenkov <minikspb@gmail.com>
License: Apache License
Project-URL: Chat: Telegram, https://t.me/sirius_sdk
Project-URL: CI: Travis, https://travis-ci.com/github/Sirius-social/sirius-sdk-python/builds
Project-URL: GitHub: issues, https://github.com/Sirius-social/sirius-sdk-python/issues
Project-URL: GitHub: repo, https://github.com/Sirius-social/sirius-sdk-python
Keywords: didcomm,sdk,self-sovereign-identity,ssi,smart-contract
Classifier: License :: OSI Approved :: Apache Software License
Classifier: Intended Audience :: Developers
Classifier: Programming Language :: Python :: 3
Classifier: Programming Language :: Python :: 3.7
Classifier: Programming Language :: Python :: 3.8
Classifier: Operating System :: POSIX
Classifier: Operating System :: MacOS :: MacOS X
Classifier: Operating System :: Microsoft :: Windows
Requires-Python: >=3.7
License-File: LICENSE
Requires-Dist: aiofiles (>=0.8.0)
Requires-Dist: aiohttp (>=3.7.4)
Requires-Dist: base58 (>=2.0.0)
Requires-Dist: multipledispatch (==0.6.0)
Requires-Dist: PyNaCl (==1.3.0)
Requires-Dist: pyqrcode (==1.2.1)
Requires-Dist: python-dateutil (>=2.8.1)
Requires-Dist: pytime (>=0.2.0)
Requires-Dist: semver (>=2.10.1)
Requires-Dist: sortedcontainers (~=2.3.0)
